nonebot_plugin_nagabus/__init__.py
nonebot_plugin_nagabus/ac.py
nonebot_plugin_nagabus/config.py
nonebot_plugin_nagabus/data/__init__.py
nonebot_plugin_nagabus/data/base.py
nonebot_plugin_nagabus/data/mjs.py
nonebot_plugin_nagabus/data/naga.py
nonebot_plugin_nagabus/data/naga_cookies.py
nonebot_plugin_nagabus/data/utils/__init__.py
nonebot_plugin_nagabus/data/utils/atomic_cache.py
nonebot_plugin_nagabus/data/utils/utc_datetime.py
nonebot_plugin_nagabus/datastore.py
nonebot_plugin_nagabus/errors.py
nonebot_plugin_nagabus/matchers/__init__.py
nonebot_plugin_nagabus/matchers/errors.py
nonebot_plugin_nagabus/matchers/naga_analyze.py
nonebot_plugin_nagabus/matchers/naga_set_cookies.py
nonebot_plugin_nagabus/matchers/naga_statistic.py
nonebot_plugin_nagabus/migrations/24aec3c56623_.py
nonebot_plugin_nagabus/migrations/70ff5fb4923e_.py
nonebot_plugin_nagabus/migrations/ab4d80c20047_.py
nonebot_plugin_nagabus/naga/__init__.py
nonebot_plugin_nagabus/naga/api.py
nonebot_plugin_nagabus/naga/errors.py
nonebot_plugin_nagabus/naga/fake_api.py
nonebot_plugin_nagabus/naga/model.py
nonebot_plugin_nagabus/naga/service.py
nonebot_plugin_nagabus/naga/utils.py
nonebot_plugin_nagabus/utils/__init__.py
nonebot_plugin_nagabus/utils/mapping.py
nonebot_plugin_nagabus/utils/nickname.py
nonebot_plugin_nagabus/utils/tz.py
nonebot_plugin_nagabus-0.3.2.dist-info/LICENSE
nonebot_plugin_nagabus-0.3.2.dist-info/METADATA
nonebot_plugin_nagabus-0.3.2.dist-info/WHEEL
nonebot_plugin_nagabus-0.3.2.dist-info/RECORD
