Metadata-Version: 2.1
Name: nonebot-plugin-nagabus
Version: 0.3.2
Summary: 
Author: ssttkkl
Author-email: huang.wen.long@hotmail.com
Requires-Python: >=3.9,<4.0
Classifier: Programming Language :: Python :: 3
Classifier: Programming Language :: Python :: 3.9
Classifier: Programming Language :: Python :: 3.10
Classifier: Programming Language :: Python :: 3.11
Requires-Dist: aiofiles (>=23.2.1,<24.0.0)
Requires-Dist: monthdelta (>=0.9.1)
Requires-Dist: nonebot-adapter-onebot (>=2.2.3)
Requires-Dist: nonebot-plugin-access-control-api (>=1.1.2,<2.0.0)
Requires-Dist: nonebot-plugin-datastore (>=1.1.0,<2.0.0)
Requires-Dist: nonebot-plugin-localstore (>=0.5.1,<0.6.0)
Requires-Dist: nonebot-plugin-majsoul (>=0.2.5,<0.3.0)
Requires-Dist: nonebot-plugin-send-anything-anywhere (>=0.3.0,<0.4.0)
Requires-Dist: nonebot-plugin-session (>=0.2.0,<0.3.0)
Requires-Dist: nonebot-plugin-session-orm (>=0.1.0,<0.2.0)
Requires-Dist: nonebot2[httpx] (>=2.0.0,<3.0.0)
Requires-Dist: pydantic (>=1.10.8,<2.0.0)
Requires-Dist: ssttkkl-nonebot-utils (>=0.1.15)
Requires-Dist: typing-extensions (>=4.6.2)
